{
  "$schema": "https://raw.githubusercontent.com/spdx/spdx-spec/v2.2.1/schemas/spdx-schema.json",
  "spdxVersion": "SPDX-2.2",
  "dataLicense": "CC0-1.0",
  "SPDXID": "SPDXRef-DOCUMENT",
  "documentNamespace": "https://spdx.org/spdxdocs/assimp-x64-windows-5.4.3-963d8a86-2133-4fd2-b513-7980efc01597",
  "name": "assimp:x64-windows@5.4.3 d9a830fa9fa889c41d203796cc29a6fbe23cce78dd2e4aae4a6c4706b5ed1485",
  "creationInfo": {
    "creators": [
      "Tool: vcpkg-2025-05-19-ece4c0f6b8fae9e94513d544c7aa753dd2c82337"
    ],
    "created": "2025-05-26T02:17:30Z"
  },
  "relationships": [
    {
      "spdxElementId": "SPDXRef-port",
      "relationshipType": "GENERATES",
      "relatedSpdxElement": "SPDXRef-binary"
    },
    {
      "spdxElementId": "SPDXRef-port",
      "relationshipType": "CONTAINS",
      "relatedSpdxElement": "SPDXRef-file-0"
    },
    {
      "spdxElementId": "SPDXRef-port",
      "relationshipType": "CONTAINS",
      "relatedSpdxElement": "SPDXRef-file-1"
    },
    {
      "spdxElementId": "SPDXRef-port",
      "relationshipType": "CONTAINS",
      "relatedSpdxElement": "SPDXRef-file-2"
    },
    {
      "spdxElementId": "SPDXRef-binary",
      "relationshipType": "GENERATED_FROM",
      "relatedSpdxElement": "SPDXRef-port"
    },
    {
      "spdxElementId": "SPDXRef-file-0",
      "relationshipType": "CONTAINED_BY",
      "relatedSpdxElement": "SPDXRef-port"
    },
    {
      "spdxElementId": "SPDXRef-file-1",
      "relationshipType": "CONTAINED_BY",
      "relatedSpdxElement": "SPDXRef-port"
    },
    {
      "spdxElementId": "SPDXRef-file-2",
      "relationshipType": "CONTAINED_BY",
      "relatedSpdxElement": "SPDXRef-port"
    },
    {
      "spdxElementId": "SPDXRef-file-2",
      "relationshipType": "DEPENDENCY_MANIFEST_OF",
      "relatedSpdxElement": "SPDXRef-port"
    }
  ],
  "packages": [
    {
      "name": "assimp",
      "SPDXID": "SPDXRef-port",
      "versionInfo": "5.4.3",
      "downloadLocation": "git+https://github.com/microsoft/vcpkg@3356e9c8083aae3cfcd24dd3269b45e2cae3173f",
      "homepage": "https://github.com/assimp/assimp",
      "licenseConcluded": "BSD-3-Clause",
      "licenseDeclared": "NOASSERTION",
      "copyrightText": "NOASSERTION",
      "description": "The Open Asset import library",
      "comment": "This is the port (recipe) consumed by vcpkg."
    },
    {
      "name": "assimp:x64-windows",
      "SPDXID": "SPDXRef-binary",
      "versionInfo": "d9a830fa9fa889c41d203796cc29a6fbe23cce78dd2e4aae4a6c4706b5ed1485",
      "downloadLocation": "NONE",
      "licenseConcluded": "BSD-3-Clause",
      "licenseDeclared": "NOASSERTION",
      "copyrightText": "NOASSERTION",
      "comment": "This is a binary package built by vcpkg."
    },
    {
      "SPDXID": "SPDXRef-resource-0",
      "name": "assimp/assimp",
      "downloadLocation": "git+https://github.com/assimp/assimp@v5.4.3",
      "licenseConcluded": "NOASSERTION",
      "licenseDeclared": "NOASSERTION",
      "copyrightText": "NOASSERTION",
      "checksums": [
        {
          "algorithm": "SHA512",
          "checksumValue": "4738db84068d36face8caf61c0789178fdfc1310fa8e81ffb9b025e14183bde546b784d691c92438ab310a79ab7b75ab62ee0247d5f01e81ddf04fb94b7a9c0b"
        }
      ]
    }
  ],
  "files": [
    {
      "fileName": "./build_fixes.patch",
      "SPDXID": "SPDXRef-file-0",
      "checksums": [
        {
          "algorithm": "SHA256",
          "checksumValue": "f7853f403859d9b22afe5c285792937f02dc1a83db45762bf306073b2c7a29b8"
        }
      ],
      "licenseConcluded": "NOASSERTION",
      "copyrightText": "NOASSERTION"
    },
    {
      "fileName": "./portfile.cmake",
      "SPDXID": "SPDXRef-file-1",
      "checksums": [
        {
          "algorithm": "SHA256",
          "checksumValue": "db5d633a0b23afcc3b8393200c56a72677b3d31d7b6b362f6a14f577c54922b8"
        }
      ],
      "licenseConcluded": "NOASSERTION",
      "copyrightText": "NOASSERTION"
    },
    {
      "fileName": "./vcpkg.json",
      "SPDXID": "SPDXRef-file-2",
      "checksums": [
        {
          "algorithm": "SHA256",
          "checksumValue": "69ef5b42d7897d47f0e356ab2e8812b440b584bc0ab0b4bd0da9fcbde3c77f3c"
        }
      ],
      "licenseConcluded": "NOASSERTION",
      "copyrightText": "NOASSERTION"
    }
  ]
}
